pyTRACK_CMIP6-1.3.6.dist-info/DESCRIPTION.rst
pyTRACK_CMIP6-1.3.6.dist-info/METADATA
pyTRACK_CMIP6-1.3.6.dist-info/RECORD
pyTRACK_CMIP6-1.3.6.dist-info/WHEEL
pyTRACK_CMIP6-1.3.6.dist-info/metadata.json
pyTRACK_CMIP6-1.3.6.dist-info/top_level.txt
track_wrapper/__init__.py
track_wrapper/track_wrapper.py
