Metadata-Version: 2.0
Name: pyTRACK-CMIP6
Version: 1.3.6
Summary: TRACK wrapper for CMIP6
Home-page: UNKNOWN
Author: acse-hvs119
Author-email: UNKNOWN
License: UNKNOWN
Platform: UNKNOWN
